MANIFEST.in
README.md
setup.cfg
setup.py
pkCal/__init__.py
pkCal/app.py
pkCal/mycalculator.py
pkCal.egg-info/PKG-INFO
pkCal.egg-info/SOURCES.txt
pkCal.egg-info/dependency_links.txt
pkCal.egg-info/entry_points.txt
pkCal.egg-info/requires.txt
pkCal.egg-info/top_level.txt
pkCal/static/index.html
pkCal/static/css/main.css
pkCal/static/css/style.css
pkCal/templates/index.html
pkCal/templates/results.html