Metadata-Version: 1.1
Name: pkCal
Version: 0.1
Summary: Simple Arithmetic Calculator
Home-page: UNKNOWN
Author: Phani Siginamsetty
Author-email: siginamsettyphani@gmail.com
License: MIT
Keywords: calculator
Platform: UNKNOWN
Classifier: Development Status :: 3 - Alpha
Classifier: Intended Audience :: Developers
Classifier: Topic :: Software Development :: Build Tools
Classifier: License :: OSI Approved :: MIT License
Classifier: Programming Language :: Python :: 3
Classifier: Programming Language :: Python :: 3.4
Classifier: Programming Language :: Python :: 3.5
Classifier: Programming Language :: Python :: 3.6
